LICENSE
README.md
setup.py
dpcrpy/__init__.py
dpcrpy.egg-info/PKG-INFO
dpcrpy.egg-info/SOURCES.txt
dpcrpy.egg-info/dependency_links.txt
dpcrpy.egg-info/top_level.txt
dpcrpy/bitMethods/__init__.py
dpcrpy/bitMethods/abcrg.py
dpcrpy/bitMethods/bcrg.py
dpcrpy/bitMethods/fda.py
dpcrpy/framework/__init__.py
dpcrpy/framework/dpcrMech.py
dpcrpy/framework/framework.py
dpcrpy/framework/noiMech.py
dpcrpy/naiveMethods/__init__.py
dpcrpy/naiveMethods/simpleMech.py
dpcrpy/naiveMethods/twoLevel.py
dpcrpy/treeMethods/__init__.py
dpcrpy/treeMethods/binMech.py
dpcrpy/utils/__init__.py
dpcrpy/utils/bitOps.py
dpcrpy/utils/dpTools/__init__.py
dpcrpy/utils/dpTools/autodp_core.py
dpcrpy/utils/dpTools/calibrator_zoo.py
dpcrpy/utils/dpTools/converter.py
dpcrpy/utils/dpTools/dp_acct.py
dpcrpy/utils/dpTools/dp_bank.py
dpcrpy/utils/dpTools/fdp_bank.py
dpcrpy/utils/dpTools/mechanism_zoo.py
dpcrpy/utils/dpTools/privacy_calibrator.py
dpcrpy/utils/dpTools/rdp_acct.py
dpcrpy/utils/dpTools/rdp_bank.py
dpcrpy/utils/dpTools/transformer_zoo.py
dpcrpy/utils/dpTools/utils.py